fast_utils
