Metadata-Version: 1.1
Name: fast-utils
Version: 0.0.6
Summary: fast-utils is a collection of small Python function that can make you scripts more fast.
Home-page: https://github.com/Lispython/fast_utils
Author: Alexandr Lispython
Author-email: alex@obout.ru
License: BSD
Platform: Linux
Platform: Mac
Classifier: Environment :: Web Environment
Classifier: License :: OSI Approved :: BSD License
Classifier: Programming Language :: Python
Classifier: Programming Language :: Python :: 2.6
Classifier: Programming Language :: Python :: 2.7
Classifier: Programming Language :: Python :: 3.2
Classifier: Operating System :: MacOS :: MacOS X
Classifier: Operating System :: POSIX
Classifier: Topic :: Utilities
Classifier: Topic :: Internet
Classifier: Topic :: Software Development :: Libraries :: Python Modules
Classifier: Intended Audience :: Developers
Classifier: Topic :: Software Development :: Libraries
Classifier: Development Status :: 5 - Production/Stable
